hjs/__init__.py
hjs/version.py
hjs/tests/__init__.py
hjs/tests/test_hjs.py
hjs-1.1.7.dist-info/METADATA
hjs-1.1.7.dist-info/WHEEL
hjs-1.1.7.dist-info/dependency_links.txt
hjs-1.1.7.dist-info/top_level.txt
hjs-1.1.7.dist-info/RECORD
